[
  {
    "text": "今日はチーズINウインナー&卵焼きのおにぎり定食を食べました。おいしかったです。",
    "imageUrl": "/scraped-images/menu_sense_kabu_1754151737108_0.jpg",
    "date": "2024-11-30T09:30:04.000Z",
    "menuName": "今日はチーズINウインナー&卵焼きのおにぎり",
    "ingredients": [
      "醤油",
      "塩",
      "胡椒",
      "油",
      "ご飯"
    ]
  },
  {
    "text": "今日はシャウエッセン&ポテサラのおにぎり定食を食べました。おいしかったです。",
    "imageUrl": "/scraped-images/menu_sense_kabu_1754151737225_1.jpg",
    "date": "2025-02-08T09:32:30.000Z",
    "menuName": "今日はシャウエッセン&ポテサラのおにぎり",
    "ingredients": [
      "醤油",
      "塩",
      "胡椒",
      "油",
      "ご飯"
    ]
  },
  {
    "text": "今日はポークビッツピラミッド&卵焼き定食を食べました。おいしかったです。",
    "imageUrl": "/scraped-images/menu_sense_kabu_1754151737251_2.jpg",
    "date": "2024-06-06T09:07:11.000Z",
    "menuName": "今日はポークビッツピラミッド&卵焼き",
    "ingredients": [
      "醤油",
      "塩",
      "胡椒",
      "油",
      "ご飯"
    ]
  },
  {
    "text": "今日はシャウエッセン卵焼き&おおきなおおきな焼きおにぎり定食を食べました。おいしかったです。",
    "imageUrl": "/scraped-images/menu_sense_kabu_1754151737274_3.jpg",
    "date": "2024-06-22T09:05:58.000Z",
    "menuName": "今日はシャウエッセン卵焼き&おおきなおおきな焼きおにぎり",
    "ingredients": [
      "醤油",
      "塩",
      "胡椒",
      "油",
      "ご飯"
    ]
  },
  {
    "text": "今日はうまトマハンバーグ定食を食べました。おいしかったです。",
    "imageUrl": "/scraped-images/menu_sense_kabu_1754151737294_4.jpg",
    "date": "2025-03-04T12:22:21.000Z",
    "menuName": "今日はうまトマハンバーグ",
    "ingredients": [
      "牛ひき肉",
      "豚ひき肉",
      "玉ねぎ",
      "パン粉",
      "卵",
      "牛乳",
      "ご飯"
    ]
  },
  {
    "text": "今日はピーマンのパリパリ揚げスイートチリソースがけ&明太卵焼き定食を食べました。おいしかったです。",
    "imageUrl": "/scraped-images/menu_sense_kabu_1754151737315_5.jpg",
    "date": "2023-12-06T09:25:45.000Z",
    "menuName": "今日はピーマンのパリパリ揚げスイートチリソースがけ&明太卵焼き",
    "ingredients": [
      "醤油",
      "塩",
      "胡椒",
      "油",
      "ご飯"
    ]
  },
  {
    "text": "今日はにんにく醤油漬けの鶏もも唐揚げ定食を食べました。おいしかったです。",
    "imageUrl": "/scraped-images/menu_sense_kabu_1754151737337_6.jpg",
    "date": "2025-03-13T09:21:17.000Z",
    "menuName": "今日はにんにく醤油漬けの鶏もも唐揚げ",
    "ingredients": [
      "鶏肉",
      "醤油",
      "生姜",
      "にんにく",
      "片栗粉",
      "油",
      "ご飯"
    ]
  },
  {
    "text": "今日はアスパラの肉巻きタルタル定食を食べました。おいしかったです。",
    "imageUrl": "/scraped-images/menu_sense_kabu_1754151737357_7.jpg",
    "date": "2025-07-03T09:24:27.000Z",
    "menuName": "今日はアスパラの肉巻きタルタル",
    "ingredients": [
      "醤油",
      "塩",
      "胡椒",
      "油",
      "ご飯"
    ]
  },
  {
    "text": "今日はオクラの肉巻き定食を食べました。おいしかったです。",
    "imageUrl": "/scraped-images/menu_sense_kabu_1754151737379_8.jpg",
    "date": "2025-06-22T09:11:38.000Z",
    "menuName": "今日はオクラの肉巻き",
    "ingredients": [
      "醤油",
      "塩",
      "胡椒",
      "油",
      "ご飯"
    ]
  }
]